nonebot_plugin_wait_a_minute-0.4.0.dist-info/METADATA
nonebot_plugin_wait_a_minute-0.4.0.dist-info/WHEEL
nonebot_plugin_wait_a_minute-0.4.0.dist-info/entry_points.txt
nonebot_plugin_wait_a_minute-0.4.0.dist-info/licenses/LICENSE
nonebot_plugin_wait_a_minute/__init__.py
nonebot_plugin_wait_a_minute/config.py
nonebot_plugin_wait_a_minute/py.typed
nonebot_plugin_wait_a_minute-0.4.0.dist-info/RECORD
