Metadata-Version: 2.1
Name: nonebot-plugin-wait-a-minute
Version: 0.4.0
Summary: A nonebot plugin for running some func before closing the bot
Author-Email: shoucandanghehe <wallfjjd@gmail.com>
License: MIT
Requires-Python: >=3.9
Requires-Dist: nonebot2>=2.3.3
